rodc_cli/__init__.py
rodc_cli/rodc.py
rodc_cli-0.1.1.dist-info/METADATA
rodc_cli-0.1.1.dist-info/WHEEL
rodc_cli-0.1.1.dist-info/entry_points.txt
rodc_cli-0.1.1.dist-info/RECORD
