Metadata-Version: 2.1
Name: rodc-cli
Version: 0.1.1
Summary: Push files to an RODC instance
Home-page: https://rodc.amyip.net
License: GPL-2.0-or-later
Author: Amy Parker
Author-email: amy@amyip.net
Requires-Python: >=3.11,<4.0
Classifier: License :: OSI Approved :: GNU General Public License v2 or later (GPLv2+)
Classifier: Programming Language :: Python :: 3
Classifier: Programming Language :: Python :: 3.11
Classifier: Programming Language :: Python :: 3.12
Requires-Dist: requests (>=2.31.0,<3.0.0)
Project-URL: Repository, https://github.com/amyipdecv/rodc
